{
  "active": false,
  "connections": {
    "When clicking ‘Test workflow’": {
      "main": [
        [
          {
            "node": "MySQL",
            "type": "main",
            "index": 0
          }
        ]
      ]
    },
    "MySQL": {
      "main": [
        [
          {
            "node": "Code",
            "type": "main",
            "index": 0
          }
        ]
      ]
    },
    "Edit Fields": {
      "main": [
        [
          {
            "node": "Loop Over Items",
            "type": "main",
            "index": 0
          }
        ]
      ]
    },
    "If": {
      "main": [
        [
          {
            "node": "BD GERSSON PRINCIPAL",
            "type": "main",
            "index": 0
          }
        ]
      ]
    },
    "BD GERSSON PRINCIPAL": {
      "main": [
        [
          {
            "node": "ES TD?",
            "type": "main",
            "index": 0
          }
        ]
      ]
    },
    "NOMBRE": {
      "main": [
        [
          {
            "node": "busqueda",
            "type": "main",
            "index": 0
          }
        ]
      ]
    },
    "busqueda": {
      "main": [
        [
          {
            "node": "no existe?",
            "type": "main",
            "index": 0
          }
        ]
      ]
    },
    "no existe?": {
      "main": [
        [
          {
            "node": "escritura",
            "type": "main",
            "index": 0
          }
        ],
        [
          {
            "node": "Loop Over Items",
            "type": "main",
            "index": 0
          }
        ]
      ]
    },
    "encontrar": {
      "main": [
        [
          {
            "node": "tag manychat",
            "type": "main",
            "index": 0
          }
        ]
      ]
    },
    "ES TD?": {
      "main": [
        [
          {
            "node": "VENEZUELA?1",
            "type": "main",
            "index": 0
          }
        ],
        [
          {
            "node": "BD GERSSON PRINCIPAL1",
            "type": "main",
            "index": 0
          }
        ]
      ]
    },
    "VENEZUELA?1": {
      "main": [
        [
          {
            "node": "ELIMINAR +58",
            "type": "main",
            "index": 0
          }
        ],
        [
          {
            "node": "NOMBRE",
            "type": "main",
            "index": 0
          },
          {
            "node": "encontrar",
            "type": "main",
            "index": 0
          }
        ]
      ]
    },
    "Code": {
      "main": [
        [
          {
            "node": "Edit Fields",
            "type": "main",
            "index": 0
          }
        ]
      ]
    },
    "Loop Over Items": {
      "main": [
        [],
        [
          {
            "node": "Wait",
            "type": "main",
            "index": 0
          }
        ]
      ]
    },
    "Wait": {
      "main": [
        [
          {
            "node": "If",
            "type": "main",
            "index": 0
          }
        ]
      ]
    },
    "escritura": {
      "main": [
        [
          {
            "node": "Loop Over Items",
            "type": "main",
            "index": 0
          }
        ]
      ]
    },
    "tag manychat": {
      "main": [
        [],
        [
          {
            "node": "Loop Over Items",
            "type": "main",
            "index": 0
          }
        ]
      ]
    },
    "ELIMINAR +58": {
      "main": [
        []
      ]
    },
    "BD GERSSON PRINCIPAL1": {
      "main": [
        [
          {
            "node": "ES TD?1",
            "type": "main",
            "index": 0
          }
        ]
      ]
    },
    "NOMBRE1": {
      "main": [
        [
          {
            "node": "busqueda1",
            "type": "main",
            "index": 0
          }
        ]
      ]
    },
    "busqueda1": {
      "main": [
        [
          {
            "node": "no existe?1",
            "type": "main",
            "index": 0
          }
        ]
      ]
    },
    "no existe?1": {
      "main": [
        [
          {
            "node": "escritura1",
            "type": "main",
            "index": 0
          }
        ],
        [
          {
            "node": "Loop Over Items",
            "type": "main",
            "index": 0
          }
        ]
      ]
    },
    "ES TD?1": {
      "main": [
        [
          {
            "node": "VENEZUELA?",
            "type": "main",
            "index": 0
          }
        ],
        [
          {
            "node": "BD GERSSON PRINCIPAL2",
            "type": "main",
            "index": 0
          }
        ]
      ]
    },
    "VENEZUELA?": {
      "main": [
        [
          {
            "node": "ELIMINAR +",
            "type": "main",
            "index": 0
          }
        ],
        [
          {
            "node": "NOMBRE1",
            "type": "main",
            "index": 0
          }
        ]
      ]
    },
    "BD GERSSON PRINCIPAL2": {
      "main": [
        [
          {
            "node": "ES TD?2",
            "type": "main",
            "index": 0
          }
        ]
      ]
    },
    "NOMBRE2": {
      "main": [
        [
          {
            "node": "busqueda2",
            "type": "main",
            "index": 0
          }
        ]
      ]
    },
    "busqueda2": {
      "main": [
        [
          {
            "node": "no existe?2",
            "type": "main",
            "index": 0
          }
        ]
      ]
    },
    "no existe?2": {
      "main": [
        [
          {
            "node": "escritura2",
            "type": "main",
            "index": 0
          }
        ],
        [
          {
            "node": "Loop Over Items",
            "type": "main",
            "index": 0
          }
        ]
      ]
    },
    "ES TD?2": {
      "main": [
        [
          {
            "node": "VENEZUELA?2",
            "type": "main",
            "index": 0
          }
        ],
        [
          {
            "node": "Loop Over Items",
            "type": "main",
            "index": 0
          }
        ]
      ]
    },
    "VENEZUELA?2": {
      "main": [
        [
          {
            "node": "ELIMINAR +1",
            "type": "main",
            "index": 0
          }
        ],
        [
          {
            "node": "NOMBRE2",
            "type": "main",
            "index": 0
          }
        ]
      ]
    },
    "escritura1": {
      "main": [
        [
          {
            "node": "Loop Over Items",
            "type": "main",
            "index": 0
          }
        ]
      ]
    },
    "escritura2": {
      "main": [
        [
          {
            "node": "Loop Over Items",
            "type": "main",
            "index": 0
          }
        ]
      ]
    }
  },
  "createdAt": "2025-05-16T17:44:51.481Z",
  "id": "U2Wp8RibMXlo9AF4",
  "isArchived": true,
  "meta": {
    "templateCredsSetupCompleted": true
  },
  "name": "My workflow 2",
  "nodes": [
    {
      "parameters": {},
      "type": "n8n-nodes-base.manualTrigger",
      "typeVersion": 1,
      "position": [
        -660,
        -80
      ],
      "id": "7d807c65-27a6-42e1-9a44-f727c475f966",
      "name": "When clicking ‘Test workflow’"
    },
    {
      "parameters": {
        "operation": "select",
        "table": {
          "__rl": true,
          "value": "ERRORES_ESCRITURA",
          "mode": "list",
          "cachedResultName": "ERRORES_ESCRITURA"
        },
        "returnAll": true,
        "options": {}
      },
      "type": "n8n-nodes-base.mySql",
      "typeVersion": 2.4,
      "position": [
        -440,
        -80
      ],
      "id": "6c3b5d53-cf8a-4f5f-a005-dc0b9ab891fa",
      "name": "MySQL",
      "credentials": {
        "mySql": {
          "id": "n8fCALXWnGdmJkBN",
          "name": "CAPTACIONES"
        }
      }
    },
    {
      "parameters": {
        "assignments": {
          "assignments": [
            {
              "id": "ffaf95ee-b40d-432a-9617-9c7a4dff4ed5",
              "name": "grupo",
              "value": "={{ $json.data.main[0][0].json.body.data.id }}",
              "type": "string"
            },
            {
              "id": "e3a70e61-aa10-4899-baff-8492afba8c37",
              "name": "numero",
              "value": "={{ $json.data.main[0][0].json.body.data.participants }}",
              "type": "string"
            },
            {
              "id": "05f7d46c-8fc2-4fc3-8cfe-c7cc00bed18b",
              "name": "accion",
              "value": "={{ $json.data.main[0][0].json.body.data.action }}",
              "type": "string"
            },
            {
              "id": "0af64330-fa8a-48d3-a8f5-3f7f13e2c9bf",
              "name": "instancia",
              "value": "={{ $json.data.main[0][0].json.body.instance }}",
              "type": "string"
            },
            {
              "id": "5c4def43-1430-4aa4-abf9-f978f042e648",
              "name": "startTime",
              "value": "={{ $json.startTime }}",
              "type": "string"
            }
          ]
        },
        "options": {}
      },
      "id": "3077e22f-6556-415f-a02a-2d0940fd6318",
      "name": "Edit Fields",
      "type": "n8n-nodes-base.set",
      "typeVersion": 3.4,
      "position": [
        0,
        -80
      ]
    },
    {
      "parameters": {
        "conditions": {
          "options": {
            "caseSensitive": true,
            "leftValue": "",
            "typeValidation": "strict",
            "version": 2
          },
          "conditions": [
            {
              "id": "c3ed79f5-9832-4354-ad38-2b7612c87557",
              "leftValue": "={{ $json.accion }}",
              "rightValue": "/add/",
              "operator": {
                "type": "string",
                "operation": "regex"
              }
            }
          ],
          "combinator": "and"
        },
        "options": {}
      },
      "id": "3c4f3c25-7333-4f3f-910e-b9b4c8cee6df",
      "name": "If",
      "type": "n8n-nodes-base.if",
      "typeVersion": 2.2,
      "position": [
        660,
        -80
      ]
    },
    {
      "parameters": {
        "operation": "select",
        "table": {
          "__rl": true,
          "value": "GERSSON_LINKS",
          "mode": "list",
          "cachedResultName": "GERSSON_LINKS"
        },
        "limit": 1,
        "where": {
          "values": [
            {
              "column": "id",
              "value": "={{ $('If').item.json.grupo }}"
            }
          ]
        },
        "options": {}
      },
      "id": "a693a02c-4ed4-474b-a43a-d5bd93b6dcec",
      "name": "BD GERSSON PRINCIPAL",
      "type": "n8n-nodes-base.mySql",
      "typeVersion": 2.4,
      "position": [
        880,
        -80
      ],
      "alwaysOutputData": true,
      "credentials": {
        "mySql": {
          "id": "179b2UX7XsHkNW05",
          "name": "REDIRECCIONES - LANZAMIENTOS"
        }
      }
    },
    {
      "parameters": {
        "url": "=https://evolution.automscc.com/group/findGroupInfos/{{ $('Loop Over Items').item.json.instancia }}",
        "sendQuery": true,
        "queryParameters": {
          "parameters": [
            {
              "name": "groupJid",
              "value": "={{ $json.id }}"
            }
          ]
        },
        "sendHeaders": true,
        "headerParameters": {
          "parameters": [
            {
              "name": "apikey",
              "value": "429683C4C977415CAAFCCE10F7D57E11"
            }
          ]
        },
        "options": {}
      },
      "type": "n8n-nodes-base.httpRequest",
      "typeVersion": 4.2,
      "position": [
        1540,
        120
      ],
      "id": "93f17031-0e0e-4fc1-b841-fb18cef7f0fa",
      "name": "NOMBRE"
    },
    {
      "parameters": {
        "operation": "select",
        "table": {
          "__rl": true,
          "value": "GERSSON_L7_WHA",
          "mode": "list",
          "cachedResultName": "GERSSON_L7_WHA"
        },
        "returnAll": true,
        "where": {
          "values": [
            {
              "column": "whatsapp",
              "condition": "LIKE",
              "value": "=%{{ $('Loop Over Items').item.json.numero.replace(/\\D/g, '') }}%"
            }
          ]
        },
        "options": {}
      },
      "type": "n8n-nodes-base.mySql",
      "typeVersion": 2.4,
      "position": [
        1760,
        120
      ],
      "id": "06d9830f-82fa-4a62-85b9-2f0e2011a72a",
      "name": "busqueda",
      "alwaysOutputData": true,
      "credentials": {
        "mySql": {
          "id": "n8fCALXWnGdmJkBN",
          "name": "CAPTACIONES"
        }
      }
    },
    {
      "parameters": {
        "table": {
          "__rl": true,
          "value": "GERSSON_L7_WHA",
          "mode": "list",
          "cachedResultName": "GERSSON_L7_WHA"
        },
        "dataMode": "defineBelow",
        "valuesToSend": {
          "values": [
            {
              "column": "dia",
              "value": "={{ $('Loop Over Items').item.json.startTime.toDateTime('ms').format('yyyy-MM-dd') }}"
            },
            {
              "column": "hora",
              "value": "={{ $('Loop Over Items').item.json.startTime.toDateTime('ms').format('HH:mm:ss') }}"
            },
            {
              "column": "whatsapp",
              "value": "=+{{ $('Loop Over Items').item.json.numero.replace(/\\D/g, '') }}"
            },
            {
              "column": "grupo",
              "value": "={{ $('Loop Over Items').item.json.grupo }}"
            },
            {
              "column": "nombre_grupo",
              "value": "={{ $('NOMBRE').item.json.subject }}"
            },
            {
              "column": "fuente",
              "value": "FB ADS"
            }
          ]
        },
        "options": {
          "detailedOutput": true
        }
      },
      "type": "n8n-nodes-base.mySql",
      "typeVersion": 2.4,
      "position": [
        2200,
        120
      ],
      "id": "a647bc21-e6f5-4930-acca-591c77bd1c31",
      "name": "escritura",
      "credentials": {
        "mySql": {
          "id": "n8fCALXWnGdmJkBN",
          "name": "CAPTACIONES"
        }
      }
    },
    {
      "parameters": {
        "conditions": {
          "options": {
            "caseSensitive": true,
            "leftValue": "",
            "typeValidation": "strict",
            "version": 2
          },
          "conditions": [
            {
              "id": "7f3e8099-ae55-4534-a5be-217d413c0ff2",
              "leftValue": "={{ $json }}",
              "rightValue": "",
              "operator": {
                "type": "object",
                "operation": "empty",
                "singleValue": true
              }
            }
          ],
          "combinator": "and"
        },
        "options": {}
      },
      "type": "n8n-nodes-base.if",
      "typeVersion": 2.2,
      "position": [
        1980,
        120
      ],
      "id": "240567cf-5b96-465b-bb2f-1d3fa0506797",
      "name": "no existe?"
    },
    {
      "parameters": {
        "method": "POST",
        "url": "=https://evolution.automscc.com/group/updateParticipant/{{$('Loop Over Items').item.json.instancia}}?groupJid={{ $('Edit Fields').item.json.grupo }}",
        "sendHeaders": true,
        "headerParameters": {
          "parameters": [
            {
              "name": "apikey",
              "value": "429683C4C977415CAAFCCE10F7D57E11"
            }
          ]
        },
        "sendBody": true,
        "specifyBody": "json",
        "jsonBody": "=\n{ \"action\": \"remove\", \n  \n  \"participants\": [ \"{{ $('Loop Over Items').item.json.numero }}\" ] } ",
        "options": {}
      },
      "id": "a6730924-b22e-41c0-8695-8ae79dbd0c8a",
      "name": "ELIMINAR +58",
      "type": "n8n-nodes-base.httpRequest",
      "typeVersion": 4.2,
      "position": [
        1540,
        -280
      ]
    },
    {
      "parameters": {
        "collection": "=TD-L7",
        "options": {
          "limit": 1
        },
        "query": "={\n  \"whatsapp\": {\n    \"$regex\": \".*{{ $('Loop Over Items').item.json.numero.replace(/\\D/g, \"\").slice(-6) }}\",\n    \"$options\": \"i\"\n  }\n}"
      },
      "id": "a825f192-0af5-47c1-a52d-9ad714ff8644",
      "name": "encontrar",
      "type": "n8n-nodes-base.mongoDb",
      "typeVersion": 1.1,
      "position": [
        1540,
        -80
      ],
      "alwaysOutputData": true,
      "credentials": {
        "mongoDb": {
          "id": "vbsT0SoMA5A3acgH",
          "name": "BASE DE DATOS GERSSON"
        }
      }
    },
    {
      "parameters": {
        "method": "POST",
        "url": "https://api.manychat.com/fb/subscriber/addTagByName",
        "sendHeaders": true,
        "headerParameters": {
          "parameters": [
            {
              "name": "Authorization",
              "value": "Bearer 288702267651723:f96a1f26344892df99c98292741de8c9"
            },
            {
              "name": "Content-Type",
              "value": "application/json"
            },
            {
              "name": "Accept",
              "value": "application/json"
            }
          ]
        },
        "sendBody": true,
        "specifyBody": "json",
        "jsonBody": "={\n  \"subscriber_id\": {{ $json.id_manychat }},\n  \"tag_name\": \"INGRESOGRUPO-L7\"\n}",
        "options": {}
      },
      "type": "n8n-nodes-base.httpRequest",
      "typeVersion": 4.2,
      "position": [
        1760,
        -80
      ],
      "id": "bd8ea177-ef4c-48d1-875e-6e550d28aff7",
      "name": "tag manychat",
      "retryOnFail": true,
      "waitBetweenTries": 5000,
      "maxTries": 5,
      "onError": "continueErrorOutput"
    },
    {
      "parameters": {
        "conditions": {
          "options": {
            "caseSensitive": true,
            "leftValue": "",
            "typeValidation": "strict",
            "version": 2
          },
          "conditions": [
            {
              "id": "8d2037fa-e2a7-4668-901e-4ca0a27a93ab",
              "leftValue": "={{ $json.id }}",
              "rightValue": "",
              "operator": {
                "type": "string",
                "operation": "exists",
                "singleValue": true
              }
            }
          ],
          "combinator": "and"
        },
        "options": {}
      },
      "id": "c98fc535-3985-4feb-a618-a33a4efc8ac3",
      "name": "ES TD?",
      "type": "n8n-nodes-base.if",
      "typeVersion": 2.2,
      "position": [
        1100,
        -80
      ]
    },
    {
      "parameters": {
        "conditions": {
          "options": {
            "caseSensitive": true,
            "leftValue": "",
            "typeValidation": "strict",
            "version": 2
          },
          "conditions": [
            {
              "id": "6e074b0d-4663-476d-ae90-8be442f648cd",
              "leftValue": "={{ $('Edit Fields').item.json.numero }}",
              "rightValue": "58",
              "operator": {
                "type": "string",
                "operation": "startsWith"
              }
            }
          ],
          "combinator": "and"
        },
        "options": {}
      },
      "id": "0385232f-3061-476a-870b-85a7c07f7b79",
      "name": "VENEZUELA?1",
      "type": "n8n-nodes-base.if",
      "typeVersion": 2.2,
      "position": [
        1320,
        -80
      ]
    },
    {
      "parameters": {
        "jsCode": "const results = [];\n\nfor (const item of items) {\n  try {\n    const bodyStr = item.json.body;\n    const parsedArray = JSON.parse(bodyStr);\n\n    // Verificar que es un array\n    if (Array.isArray(parsedArray)) {\n      for (const obj of parsedArray) {\n        if (obj && typeof obj === 'object') {\n          results.push({ json: obj });\n        }\n      }\n    } else if (typeof parsedArray === 'object') {\n      results.push({ json: parsedArray });\n    } else {\n      results.push({\n        json: {\n          error: 'Parsed content is not an object or array',\n          original: bodyStr\n        }\n      });\n    }\n\n  } catch (error) {\n    results.push({\n      json: {\n        error: 'Error parsing JSON',\n        original: item.json.body,\n        details: error.message\n      }\n    });\n  }\n}\n\nreturn results;\n"
      },
      "type": "n8n-nodes-base.code",
      "typeVersion": 2,
      "position": [
        -220,
        -80
      ],
      "id": "d311f23a-de51-427d-ac1a-262351f0f531",
      "name": "Code"
    },
    {
      "parameters": {
        "options": {}
      },
      "type": "n8n-nodes-base.splitInBatches",
      "typeVersion": 3,
      "position": [
        220,
        -80
      ],
      "id": "54ee8d35-447f-4b23-8217-57a7f5217e4b",
      "name": "Loop Over Items"
    },
    {
      "parameters": {
        "amount": 1
      },
      "type": "n8n-nodes-base.wait",
      "typeVersion": 1.1,
      "position": [
        440,
        -80
      ],
      "id": "3033f4f3-28f7-4bc9-9923-bb655763f630",
      "name": "Wait",
      "webhookId": "a88fda3f-380f-4aee-bc79-6ec15d8cca45"
    },
    {
      "parameters": {
        "operation": "select",
        "table": {
          "__rl": true,
          "value": "GIORGIO_LINKS",
          "mode": "list",
          "cachedResultName": "GIORGIO_LINKS"
        },
        "limit": 1,
        "where": {
          "values": [
            {
              "column": "id",
              "value": "={{ $('If').item.json.grupo }}"
            }
          ]
        },
        "options": {}
      },
      "id": "20ad8dfc-a875-440b-9324-4d2d580d4840",
      "name": "BD GERSSON PRINCIPAL1",
      "type": "n8n-nodes-base.mySql",
      "typeVersion": 2.4,
      "position": [
        1160,
        640
      ],
      "alwaysOutputData": true,
      "credentials": {
        "mySql": {
          "id": "179b2UX7XsHkNW05",
          "name": "REDIRECCIONES - LANZAMIENTOS"
        }
      }
    },
    {
      "parameters": {
        "url": "=https://evolution.automscc.com/group/findGroupInfos/{{ $('Loop Over Items').item.json.instancia }}",
        "sendQuery": true,
        "queryParameters": {
          "parameters": [
            {
              "name": "groupJid",
              "value": "={{ $json.id }}"
            }
          ]
        },
        "sendHeaders": true,
        "headerParameters": {
          "parameters": [
            {
              "name": "apikey",
              "value": "429683C4C977415CAAFCCE10F7D57E11"
            }
          ]
        },
        "options": {}
      },
      "type": "n8n-nodes-base.httpRequest",
      "typeVersion": 4.2,
      "position": [
        1820,
        720
      ],
      "id": "aaf35a25-03d0-4e43-a9f3-b1b2b9c6c522",
      "name": "NOMBRE1"
    },
    {
      "parameters": {
        "operation": "select",
        "table": {
          "__rl": true,
          "value": "GIORGIO_L1_WHA",
          "mode": "list",
          "cachedResultName": "GIORGIO_L1_WHA"
        },
        "returnAll": true,
        "where": {
          "values": [
            {
              "column": "whatsapp",
              "condition": "LIKE",
              "value": "=%{{ $('Loop Over Items').item.json.numero.replace(/\\D/g, '') }}%"
            }
          ]
        },
        "options": {}
      },
      "type": "n8n-nodes-base.mySql",
      "typeVersion": 2.4,
      "position": [
        2040,
        720
      ],
      "id": "f6757971-ebf7-4e9d-8cef-d9f622cbccac",
      "name": "busqueda1",
      "alwaysOutputData": true,
      "credentials": {
        "mySql": {
          "id": "n8fCALXWnGdmJkBN",
          "name": "CAPTACIONES"
        }
      }
    },
    {
      "parameters": {
        "table": {
          "__rl": true,
          "value": "GIORGIO_L1_WHA",
          "mode": "list",
          "cachedResultName": "GIORGIO_L1_WHA"
        },
        "dataMode": "defineBelow",
        "valuesToSend": {
          "values": [
            {
              "column": "dia",
              "value": "={{ $('Loop Over Items').item.json.startTime.toDateTime('ms').format('yyyy-MM-dd') }}"
            },
            {
              "column": "hora",
              "value": "={{ $('Loop Over Items').item.json.startTime.toDateTime('ms').format('HH:mm:ss') }}"
            },
            {
              "column": "whatsapp",
              "value": "=+{{ $('Loop Over Items').item.json.numero.replace(/\\D/g, '') }}"
            },
            {
              "column": "grupo",
              "value": "={{ $('Loop Over Items').item.json.grupo }}"
            },
            {
              "column": "nombre_grupo",
              "value": "={{ $('NOMBRE1').item.json.subject }}"
            },
            {
              "column": "fuente",
              "value": "FB ADS"
            }
          ]
        },
        "options": {
          "detailedOutput": true
        }
      },
      "type": "n8n-nodes-base.mySql",
      "typeVersion": 2.4,
      "position": [
        2480,
        720
      ],
      "id": "83c2ffd2-b0eb-42a8-a0c8-407cce7fafa9",
      "name": "escritura1",
      "credentials": {
        "mySql": {
          "id": "n8fCALXWnGdmJkBN",
          "name": "CAPTACIONES"
        }
      }
    },
    {
      "parameters": {
        "conditions": {
          "options": {
            "caseSensitive": true,
            "leftValue": "",
            "typeValidation": "strict",
            "version": 2
          },
          "conditions": [
            {
              "id": "7f3e8099-ae55-4534-a5be-217d413c0ff2",
              "leftValue": "={{ $json }}",
              "rightValue": "",
              "operator": {
                "type": "object",
                "operation": "empty",
                "singleValue": true
              }
            }
          ],
          "combinator": "and"
        },
        "options": {}
      },
      "type": "n8n-nodes-base.if",
      "typeVersion": 2.2,
      "position": [
        2260,
        720
      ],
      "id": "88a1a029-7682-4a42-8bfd-a780e2dd7f1e",
      "name": "no existe?1"
    },
    {
      "parameters": {
        "method": "POST",
        "url": "=https://evolution.automscc.com/group/updateParticipant/{{$('Loop Over Items').item.json.instancia}}?groupJid={{ $('Edit Fields').item.json.grupo }}",
        "sendHeaders": true,
        "headerParameters": {
          "parameters": [
            {
              "name": "apikey",
              "value": "429683C4C977415CAAFCCE10F7D57E11"
            }
          ]
        },
        "sendBody": true,
        "specifyBody": "json",
        "jsonBody": "=\n{ \"action\": \"remove\", \n  \n  \"participants\": [ \"{{ $('Loop Over Items').item.json.numero }}\" ] } ",
        "options": {}
      },
      "id": "7f1203f8-61e4-4fa8-a7e8-7b5a46c9df31",
      "name": "ELIMINAR +",
      "type": "n8n-nodes-base.httpRequest",
      "typeVersion": 4.2,
      "position": [
        1820,
        520
      ]
    },
    {
      "parameters": {
        "conditions": {
          "options": {
            "caseSensitive": true,
            "leftValue": "",
            "typeValidation": "strict",
            "version": 2
          },
          "conditions": [
            {
              "id": "8d2037fa-e2a7-4668-901e-4ca0a27a93ab",
              "leftValue": "={{ $json.id }}",
              "rightValue": "",
              "operator": {
                "type": "string",
                "operation": "exists",
                "singleValue": true
              }
            }
          ],
          "combinator": "and"
        },
        "options": {}
      },
      "id": "6a2f2b3f-48fd-40e6-8231-80aa01d02e0b",
      "name": "ES TD?1",
      "type": "n8n-nodes-base.if",
      "typeVersion": 2.2,
      "position": [
        1380,
        640
      ]
    },
    {
      "parameters": {
        "conditions": {
          "options": {
            "caseSensitive": true,
            "leftValue": "",
            "typeValidation": "strict",
            "version": 2
          },
          "conditions": [
            {
              "id": "6e074b0d-4663-476d-ae90-8be442f648cd",
              "leftValue": "={{ $('Edit Fields').item.json.numero }}",
              "rightValue": "58",
              "operator": {
                "type": "string",
                "operation": "startsWith"
              }
            }
          ],
          "combinator": "and"
        },
        "options": {}
      },
      "id": "cb7258fb-e0e0-470b-9791-fe08d944260d",
      "name": "VENEZUELA?",
      "type": "n8n-nodes-base.if",
      "typeVersion": 2.2,
      "position": [
        1600,
        640
      ]
    },
    {
      "parameters": {
        "operation": "select",
        "table": {
          "__rl": true,
          "value": "ARZA_UÑAS_LINKS",
          "mode": "list",
          "cachedResultName": "ARZA_UÑAS_LINKS"
        },
        "limit": 1,
        "where": {
          "values": [
            {
              "column": "id",
              "value": "={{ $('If').item.json.grupo }}"
            }
          ]
        },
        "options": {}
      },
      "id": "4d0b77bb-32af-4734-a167-5e5080c6d35d",
      "name": "BD GERSSON PRINCIPAL2",
      "type": "n8n-nodes-base.mySql",
      "typeVersion": 2.4,
      "position": [
        1620,
        1220
      ],
      "alwaysOutputData": true,
      "credentials": {
        "mySql": {
          "id": "179b2UX7XsHkNW05",
          "name": "REDIRECCIONES - LANZAMIENTOS"
        }
      }
    },
    {
      "parameters": {
        "url": "=https://evolution.automscc.com/group/findGroupInfos/{{ $('Loop Over Items').item.json.instancia }}",
        "sendQuery": true,
        "queryParameters": {
          "parameters": [
            {
              "name": "groupJid",
              "value": "={{ $json.id }}"
            }
          ]
        },
        "sendHeaders": true,
        "headerParameters": {
          "parameters": [
            {
              "name": "apikey",
              "value": "429683C4C977415CAAFCCE10F7D57E11"
            }
          ]
        },
        "options": {}
      },
      "type": "n8n-nodes-base.httpRequest",
      "typeVersion": 4.2,
      "position": [
        2280,
        1300
      ],
      "id": "ace048ed-59ac-4457-9fbe-651f37187f14",
      "name": "NOMBRE2"
    },
    {
      "parameters": {
        "operation": "select",
        "table": {
          "__rl": true,
          "value": "UÑAS_L2_WHA",
          "mode": "list",
          "cachedResultName": "UÑAS_L2_WHA"
        },
        "returnAll": true,
        "where": {
          "values": [
            {
              "column": "whatsapp",
              "condition": "LIKE",
              "value": "=%{{ $('Loop Over Items').item.json.numero.replace(/\\D/g, '') }}%"
            }
          ]
        },
        "options": {}
      },
      "type": "n8n-nodes-base.mySql",
      "typeVersion": 2.4,
      "position": [
        2500,
        1300
      ],
      "id": "d690840a-8da5-4b87-9c04-b60553e38643",
      "name": "busqueda2",
      "alwaysOutputData": true,
      "credentials": {
        "mySql": {
          "id": "n8fCALXWnGdmJkBN",
          "name": "CAPTACIONES"
        }
      }
    },
    {
      "parameters": {
        "table": {
          "__rl": true,
          "value": "UÑAS_L2_WHA",
          "mode": "list",
          "cachedResultName": "UÑAS_L2_WHA"
        },
        "dataMode": "defineBelow",
        "valuesToSend": {
          "values": [
            {
              "column": "dia",
              "value": "={{ $('Loop Over Items').item.json.startTime.toDateTime('ms').format('yyyy-MM-dd') }}"
            },
            {
              "column": "hora",
              "value": "={{ $('Loop Over Items').item.json.startTime.toDateTime('ms').format('HH:mm:ss') }}"
            },
            {
              "column": "whatsapp",
              "value": "=+{{ $('Loop Over Items').item.json.numero.replace(/\\D/g, '') }}"
            },
            {
              "column": "grupo",
              "value": "={{ $('Loop Over Items').item.json.grupo }}"
            },
            {
              "column": "nombre_grupo",
              "value": "={{ $('NOMBRE2').item.json.subject }}"
            },
            {
              "column": "fuente",
              "value": "FB ADS"
            }
          ]
        },
        "options": {
          "detailedOutput": true
        }
      },
      "type": "n8n-nodes-base.mySql",
      "typeVersion": 2.4,
      "position": [
        2940,
        1300
      ],
      "id": "4895e36b-6e65-4b4a-be57-b3b642c77e6b",
      "name": "escritura2",
      "credentials": {
        "mySql": {
          "id": "n8fCALXWnGdmJkBN",
          "name": "CAPTACIONES"
        }
      }
    },
    {
      "parameters": {
        "conditions": {
          "options": {
            "caseSensitive": true,
            "leftValue": "",
            "typeValidation": "strict",
            "version": 2
          },
          "conditions": [
            {
              "id": "7f3e8099-ae55-4534-a5be-217d413c0ff2",
              "leftValue": "={{ $json }}",
              "rightValue": "",
              "operator": {
                "type": "object",
                "operation": "empty",
                "singleValue": true
              }
            }
          ],
          "combinator": "and"
        },
        "options": {}
      },
      "type": "n8n-nodes-base.if",
      "typeVersion": 2.2,
      "position": [
        2720,
        1300
      ],
      "id": "19c8a8b5-a312-4224-bb96-b634d6a7976e",
      "name": "no existe?2"
    },
    {
      "parameters": {
        "method": "POST",
        "url": "=https://evolution.automscc.com/group/updateParticipant/{{$('Loop Over Items').item.json.instancia}}?groupJid={{ $('Edit Fields').item.json.grupo }}",
        "sendHeaders": true,
        "headerParameters": {
          "parameters": [
            {
              "name": "apikey",
              "value": "429683C4C977415CAAFCCE10F7D57E11"
            }
          ]
        },
        "sendBody": true,
        "specifyBody": "json",
        "jsonBody": "=\n{ \"action\": \"remove\", \n  \n  \"participants\": [ \"{{ $('Loop Over Items').item.json.numero }}\" ] } ",
        "options": {}
      },
      "id": "0d85c794-a4b7-47a1-a820-7a1623eba965",
      "name": "ELIMINAR +1",
      "type": "n8n-nodes-base.httpRequest",
      "typeVersion": 4.2,
      "position": [
        2280,
        1100
      ]
    },
    {
      "parameters": {
        "conditions": {
          "options": {
            "caseSensitive": true,
            "leftValue": "",
            "typeValidation": "strict",
            "version": 2
          },
          "conditions": [
            {
              "id": "8d2037fa-e2a7-4668-901e-4ca0a27a93ab",
              "leftValue": "={{ $json.id }}",
              "rightValue": "",
              "operator": {
                "type": "string",
                "operation": "exists",
                "singleValue": true
              }
            }
          ],
          "combinator": "and"
        },
        "options": {}
      },
      "id": "94d29d9c-a1b2-47b7-82f1-310f2857dd0c",
      "name": "ES TD?2",
      "type": "n8n-nodes-base.if",
      "typeVersion": 2.2,
      "position": [
        1840,
        1220
      ]
    },
    {
      "parameters": {
        "conditions": {
          "options": {
            "caseSensitive": true,
            "leftValue": "",
            "typeValidation": "strict",
            "version": 2
          },
          "conditions": [
            {
              "id": "6e074b0d-4663-476d-ae90-8be442f648cd",
              "leftValue": "={{ $('Edit Fields').item.json.numero }}",
              "rightValue": "58",
              "operator": {
                "type": "string",
                "operation": "startsWith"
              }
            }
          ],
          "combinator": "and"
        },
        "options": {}
      },
      "id": "acc61dea-8fb8-42f7-b2cd-40a5564c2f27",
      "name": "VENEZUELA?2",
      "type": "n8n-nodes-base.if",
      "typeVersion": 2.2,
      "position": [
        2060,
        1220
      ]
    }
  ],
  "pinData": {},
  "repo_name": "backupn8n",
  "repo_owner": "Santiagociroc11",
  "repo_path": "backup/",
  "settings": {
    "executionOrder": "v1"
  },
  "staticData": null,
  "tags": [],
  "triggerCount": 0,
  "updatedAt": "2025-06-06T17:03:01.000Z",
  "versionId": "9580ccc7-c51d-4cd6-9516-af2b4b87a173"
}